CHANGES.txt
LICENSE.txt
MANIFEST.in
README.rst
setup.py
x509/__init__.py
x509/commands.py
x509/compat.py
x509/models.py
x509.egg-info/PKG-INFO
x509.egg-info/SOURCES.txt
x509.egg-info/dependency_links.txt
x509.egg-info/entry_points.txt
x509.egg-info/not-zip-safe
x509.egg-info/requires.txt
x509.egg-info/top_level.txt
x509/pkcs7/__init__.py
x509/pkcs7/debug.py
x509/pkcs7/digest.py
x509/pkcs7/pkcs7_decoder.py
x509/pkcs7/tstamp_helper.py
x509/pkcs7/verifier.py
x509/pkcs7/asn1_models/DSA.py
x509/pkcs7/asn1_models/RSA.py
x509/pkcs7/asn1_models/TST_info.py
x509/pkcs7/asn1_models/X509_certificate.py
x509/pkcs7/asn1_models/__init__.py
x509/pkcs7/asn1_models/att_certificate_v2.py
x509/pkcs7/asn1_models/certificate_extensions.py
x509/pkcs7/asn1_models/crl.py
x509/pkcs7/asn1_models/decoder_workarounds.py
x509/pkcs7/asn1_models/digest_info.py
x509/pkcs7/asn1_models/general_types.py
x509/pkcs7/asn1_models/oid.py
x509/pkcs7/asn1_models/pkcs_signed_data.py
x509/pkcs7/asn1_models/tools.py
x509/test/__init__.py
x509/test/test_simple.py