Metadata-Version: 1.1
Name: x509
Version: 0.1
Summary: Parse x509v3 certificates and PKCS7 signatures
Home-page: https://github.com/cniemira/py3x509
Author: cniemira
Author-email: siege@siege.org
License:     This library is free software; you can redistribute it and/or
